nerdemoji/__init__.py
nerdemoji/nerdemoji.py
nerdemoji-0.0.4.dist-info/LICENSE
nerdemoji-0.0.4.dist-info/METADATA
nerdemoji-0.0.4.dist-info/WHEEL
nerdemoji-0.0.4.dist-info/top_level.txt
nerdemoji-0.0.4.dist-info/RECORD
