Metadata-Version: 2.1
Name: nerdemoji
Version: 0.0.4
Summary: Humiliate your python interpreter whenever it encounters an error
Author-email: Dosh4dolphins janitorial staff <dosh4dolphins@gmail.com>
License: GNU GENERAL PUBLIC LICENSE
Project-URL: Homepage, https://github.com/Darux/nerdemoji
Project-URL: Bug Tracker, https://github.com/Darux/nerdemoji/issues
Classifier: Programming Language :: Python :: 3
Classifier: License :: OSI Approved :: GNU General Public License v3 (GPLv3)
Classifier: Operating System :: OS Independent
Requires-Python: >=3.7
License-File: LICENSE
